cutml/__init__.py
cutml/cli.py
cutml-0.1.0.dist-info/METADATA
cutml-0.1.0.dist-info/WHEEL
cutml-0.1.0.dist-info/entry_points.txt
cutml-0.1.0.dist-info/top_level.txt
cutml-0.1.0.dist-info/RECORD
